{
  "objectID": 634649,
  "original_title": "Spider-Man: No Way Home",
  "original_language": "en",
  "release_date": 1639526400,
  "vote_average": 7,
  "vote_count": 17667,
  "popularity": 500.419,
  "year": 2021,
  "actors": [
    "Tom Holland",
    "Zendaya",
    "Benedict Cumberbatch",
    "Jacob Batalon",
    "Jon Favreau",
    "Jamie Foxx",
    "Willem Dafoe",
    "Alfred Molina",
    "Benedict Wong",
    "Tony Revolori",
    "Marisa Tomei",
    "Andrew Garfield",
    "Tobey Maguire",
    "Angourie Rice",
    "Arian Moayed",
    "Paula Newsome",
    "Hannibal Buress",
    "Martin Starr",
    "J.B. Smoove",
    "J.K. Simmons",
    "Rhys Ifans",
    "Charlie Cox",
    "Thomas Haden Church",
    "Haroon Kahn",
    "Emily Fong",
    "Mary Rivera",
    "Rudy Eisenzopf",
    "Kathleen Cardoso",
    "Jonathan Sam",
    "Andrew Dunlap",
    "Ben VanderMey",
    "Zany Dunlap",
    "B. Clutch Dunlap",
    "Minnah Dunlap",
    "Gary Weeks",
    "Gregory Konow",
    "Carol Anne Dines",
    "Anisa Nyell Johnson",
    "Willie Burton",
    "Mallory Hoff",
    "Greg Clarkson",
    "Regina Ting Chen",
    "Robert Mitchel Owenby",
    "Glenn Keogh",
    "Paris Benjamin",
    "Jwaundace Candece",
    "Taylor St. Clair",
    "Gabriella Cila",
    "Darnell Appling",
    "Rolando Fernandez",
    "Edward Force",
    "Michael Le",
    "Dean Meminger",
    "Frederick A. Brown",
    "Cristo Fernández",
    "Clay Savage",
    "Tom Hardy",
    "Jake Gyllenhaal",
    "Jay Karales",
    "Gina Aponte",
    "John Barnes",
    "Harry Holland"
  ],
  "director": "Jon Watts",
  "backdrop": "https://image.tmdb.org/t/p/w500/zD5v1E4joAzFvmAEytt7fM3ivyT.jpg",
  "title": "Spider-Man: No Way Home",
  "overview": "Peter Parker is unmasked and no longer able to separate his normal life from the high-stakes of being a super-hero. When he asks for help from Doctor Strange the stakes become even more dangerous, forcing him to discover what it truly means to be Spider-Man.",
  "genres": ["Action", "Adventure", "Science Fiction"],
  "poster": "https://image.tmdb.org/t/p/w500/1g0dhYtq4irTY1GPXvft6k4YLjm.jpg",
  "budget": 200000000,
  "revenue": 1921847111,
  "price": 7.99,
  "on_sale": false,
  "featured": false
}
